dccard/Component.py
dccard/__init__.py
dccard/canvas.py
dccard/type.py
dccard/assets/circle.ppm
dccard/modules/__init__.py
dccard/modules/display_list.py
dccard/modules/group.py
dccard/modules/image.py
dccard/modules/levelline.py
dccard/modules/text.py
dccard/util/masks.py
dccard/util/zoom.py
dccard-0.2.dist-info/METADATA
dccard-0.2.dist-info/WHEEL
dccard-0.2.dist-info/top_level.txt
dccard-0.2.dist-info/RECORD
