Metadata-Version: 2.4
Name: dccard
Version: 0.2
Summary: easu way to build image
Author-email: phillychi3 <phillychi3@gmail.com>
Project-URL: Repository, https://github.com/phillychi3/dccard.git
Keywords: image
Classifier: Programming Language :: Python :: 3
Classifier: License :: OSI Approved :: MIT License
Classifier: Operating System :: OS Independent
Requires-Python: >=3.8
Requires-Dist: pillow
Requires-Dist: requests
